{
  "/*404": [
    {
      "type": "script",
      "href": "/wss/assets/_...404_-d6eb91e1.js"
    },
    {
      "type": "script",
      "href": "/wss/assets/entry-client-842a3e3c.js"
    },
    {
      "type": "style",
      "href": "/wss/assets/entry-client-5a475cd7.css"
    }
  ],
  "/": [
    {
      "type": "script",
      "href": "/wss/assets/index-2661583f.js"
    },
    {
      "type": "script",
      "href": "/wss/assets/entry-client-842a3e3c.js"
    },
    {
      "type": "style",
      "href": "/wss/assets/entry-client-5a475cd7.css"
    },
    {
      "type": "style",
      "href": "/wss/assets/index-d8cf4c2b.css"
    }
  ],
  "entry-client": [
    {
      "type": "script",
      "href": "/wss/assets/entry-client-842a3e3c.js"
    },
    {
      "type": "style",
      "href": "/wss/assets/entry-client-5a475cd7.css"
    }
  ],
  "index.html": []
}